pyldo/__init__.py
pyldo/cli.py
pyldo/converter/__init__.py
pyldo/converter/context_generator.py
pyldo/converter/linkml_parser.py
pyldo/converter/shapetype_generator.py
pyldo/converter/shex_parser.py
pyldo/converter/type_generator.py
pyldo/dataset/__init__.py
pyldo/dataset/graph.py
pyldo/dataset/serializers.py
pyldo/dataset/subscribable.py
pyldo/dataset/transaction.py
pyldo/ldo/__init__.py
pyldo/ldo/base.py
pyldo/ldo/builder.py
pyldo/ldo/factory.py
pyldo/ldo/ldset.py
pyldo/ldo/link_query.py
pyldo/ldo/methods.py
pyldo/ldo/write_resource.py
pyldo/shapes/__init__.py
pyldo/shapes/authorization.py
pyldo/shapes/bookmark.py
pyldo/shapes/chat.py
pyldo/shapes/contact.py
pyldo/shapes/event.py
pyldo/shapes/issue.py
pyldo/shapes/location.py
pyldo/shapes/media.py
pyldo/shapes/meeting.py
pyldo/shapes/note.py
pyldo/shapes/notification.py
pyldo/shapes/post.py
pyldo/shapes/preferences.py
pyldo/shapes/project.py
pyldo/shapes/solid_profile.py
pyldo/shapes/type_index.py
pyldo/solid/__init__.py
pyldo/solid/auth.py
pyldo/solid/client.py
pyldo/solid/webid.py
pyldo-0.0.13.dist-info/METADATA
pyldo-0.0.13.dist-info/WHEEL
pyldo-0.0.13.dist-info/entry_points.txt
pyldo-0.0.13.dist-info/licenses/LICENSE
pyldo-0.0.13.dist-info/RECORD
