Metadata-Version: 2.4
Name: pyldo
Version: 0.0.13
Summary: Linked Data Objects for Python - Making RDF as easy as working with plain objects
Project-URL: Homepage, https://github.com/Mariatta/pyldo
Project-URL: Documentation, https://github.com/Mariatta/pyldo
Project-URL: Repository, https://github.com/Mariatta/pyldo
Author: Marlene Mhangami
License-Expression: MIT
License-File: LICENSE
Keywords: linked-data,linkml,rdf,semantic-web,shex,solid
Classifier: Development Status :: 2 - Pre-Alpha
Classifier: Intended Audience :: Developers
Classifier: License :: OSI Approved :: MIT License
Classifier: Programming Language :: Python :: 3
Classifier: Programming Language :: Python :: 3.10
Classifier: Programming Language :: Python :: 3.11
Classifier: Programming Language :: Python :: 3.12
Classifier: Topic :: Internet :: WWW/HTTP
Classifier: Topic :: Software Development :: Libraries :: Python Modules
Requires-Python: >=3.10
Requires-Dist: click>=8.0.0
Requires-Dist: cryptography>=41.0.0
Requires-Dist: httpx>=0.25.0
Requires-Dist: pydantic>=2.0.0
Requires-Dist: pyjwt>=2.8.0
Requires-Dist: pyshex>=0.8.1
Requires-Dist: pyyaml>=6.0.0
Requires-Dist: rdflib>=7.0.0
Requires-Dist: solid-oidc-client>=0.0.4
Provides-Extra: dev
Requires-Dist: pytest-cov>=4.0.0; extra == 'dev'
Requires-Dist: pytest>=7.0.0; extra == 'dev'
Requires-Dist: ruff>=0.1.0; extra == 'dev'
